manage.py
analytics/__init__.py
analytics/admin.py
analytics/apps.py
analytics/models.py
analytics/migrations/0001_initial.py
analytics/migrations/0002_initial.py
analytics/migrations/__init__.py
analytics/site/__init__.py
analytics/site/anlmodeladmin.py
analytics/site/closingreasonstatadmin.py
analytics/site/conversionadmin.py
analytics/site/dealstatadmin.py
analytics/site/incomestatadmin.py
analytics/site/leadsourcestatadmin.py
analytics/site/outputstatadmin.py
analytics/site/requeststatadmin.py
analytics/site/salesfunnelsadmin.py
analytics/templates/admin/analytics/closingreasonstat/closingreasons_summary_change_list.html
analytics/templates/admin/analytics/incomestat/change_list_object_tools.html
analytics/templates/admin/analytics/leadsourcestat/leadsource_summary_change_list.html
analytics/templates/admin/analytics/outputstat/change_list_object_tools.html
analytics/templates/admin/analytics/salesfunnel/sales_funnel_change_list.html
analytics/templates/analytics/bar_chart.html
analytics/templates/analytics/bar_chart_.html
analytics/templates/analytics/data_table.html
analytics/templates/analytics/notice.html
analytics/templates/analytics/outputstat.html
analytics/templates/analytics/snapshots_change_list.html
analytics/templates/analytics/summary_change_list.html
analytics/templates/analytics/view_snapshots.html
analytics/utils/__init__.py
analytics/utils/helpers.py
analytics/utils/monthly_snapshot_saving.py
chat/__init__.py
chat/admin.py
chat/apps.py
chat/models.py
chat/forms/__init__.py
chat/forms/chatmessageform.py
chat/migrations/0001_initial.py
chat/migrations/__init__.py
chat/site/__init__.py
chat/site/chatmessageadmin.py
chat/templates/chat_buttons.html
chat/templates/admin/chat/chatmessage/change_list_object_tools.html
chat/templates/admin/chat/chatmessage/submit_line.html
chat/templates/chat/chatmessage_email.html
common/__init__.py
common/admin.py
common/apps.py
common/models.py
common/settings.py
common/urls.py
common/fixtures/department.json
django_crm_admin-1.7.0.dist-info/licenses/LICENSE
django_crm_admin-1.7.0.dist-info/METADATA
django_crm_admin-1.7.0.dist-info/WHEEL
django_crm_admin-1.7.0.dist-info/top_level.txt
django_crm_admin-1.7.0.dist-info/RECORD
