Metadata-Version: 2.4
Name: django-crm-admin
Version: 1.7.0
Summary: CRM and task management software, Email marketing and many more. This Django CRM software app is built for individual use by businesses of any size or freelancers and is designed to provide easy customization and quick development.
Home-page: https://DjangoCRM.github.io/info/
Download-URL: https://sourceforge.net/projects/django-crm/files/latest/download
Author: Vadym Kharchenko
Author-email: VadKhar@outlook.com
License: AGPL-3.0-or-later
Project-URL: Homepage, https://DjangoCRM.github.io/info/
Project-URL: Source, https://github.com/DjangoCRM/django-crm
Project-URL: Documentation, https://django-crm-admin.readthedocs.io
Project-URL: Tracker, https://github.com/DjangoCRM/django-crm/issues
Project-URL: Changelog, https://github.com/DjangoCRM/django-crm/blob/main/CHANGELOG.md
Project-URL: Download, https://sourceforge.net/projects/django-crm/files/latest/download
Keywords: CRM,Django CRM,Django-CRM,Python CRM,CRM software,Analytical CRM,CRM package,Free CRM management software,mailing CRM,CRM and task management software
Classifier: Development Status :: 5 - Production/Stable
Classifier: Environment :: Web Environment
Classifier: Framework :: Django
Classifier: Framework :: Django :: 5.2
Classifier: Intended Audience :: Customer Service
Classifier: Intended Audience :: End Users/Desktop
Classifier: Intended Audience :: Developers
Classifier: Natural Language :: Arabic
Classifier: Natural Language :: Chinese (Simplified)
Classifier: Natural Language :: Czech
Classifier: Natural Language :: Dutch
Classifier: Natural Language :: English
Classifier: Natural Language :: French
Classifier: Natural Language :: German
Classifier: Natural Language :: Greek
Classifier: Natural Language :: Hindi
Classifier: Natural Language :: Indonesian
Classifier: Natural Language :: Italian
Classifier: Natural Language :: Japanese
Classifier: Natural Language :: Korean
Classifier: Natural Language :: Polish
Classifier: Natural Language :: Portuguese (Brazilian)
Classifier: Natural Language :: Russian
Classifier: Natural Language :: Spanish
Classifier: Natural Language :: Turkish
Classifier: Natural Language :: Ukrainian
Classifier: Natural Language :: Vietnamese
Classifier: Operating System :: OS Independent
Classifier: Programming Language :: Python
Classifier: Programming Language :: Python :: 3
Classifier: Programming Language :: Python :: 3 :: Only
Classifier: Programming Language :: Python :: 3.10
Classifier: Programming Language :: Python :: 3.11
Classifier: Programming Language :: Python :: 3.12
Classifier: Topic :: Office/Business
Classifier: Topic :: Office/Business :: Financial
Classifier: Topic :: Internet :: WWW/HTTP
Classifier: Topic :: Internet :: WWW/HTTP :: Dynamic Content
Requires-Python: >=3.10
License-File: LICENSE
Requires-Dist: aiohttp==3.13.2
Requires-Dist: aiosignal==1.4.0
Requires-Dist: asgiref==3.11.0
Requires-Dist: attrs==25.4.0
Requires-Dist: certifi==2025.11.12
Requires-Dist: charset-normalizer==3.4.4
Requires-Dist: Django==5.2.9
Requires-Dist: et-xmlfile==2.0.0
Requires-Dist: frozenlist==1.8.0
Requires-Dist: geoip2==5.2.0
Requires-Dist: idna==3.11
Requires-Dist: maxminddb==3.0.0
Requires-Dist: multidict==6.7.0
Requires-Dist: mysqlclient==2.2.7
Requires-Dist: numpy==2.3.5
Requires-Dist: openpyxl==3.1.5
Requires-Dist: pandas==2.3.3
Requires-Dist: polib==1.2.0
Requires-Dist: python-dateutil==2.9.0.post0
Requires-Dist: pytz==2025.2
Requires-Dist: requests==2.32.5
Requires-Dist: setuptools==80.9.0
Requires-Dist: six==1.17.0
Requires-Dist: sqlparse==0.5.4
Requires-Dist: tendo==0.3.0
Requires-Dist: tzdata==2025.2
Requires-Dist: urllib3==2.6.2
Requires-Dist: XlsxWriter==3.2.9
Requires-Dist: yarl==1.22.0
Dynamic: download-url
Dynamic: license-file
